setup.py
blocktrail/__init__.py
blocktrail/client.py
blocktrail/connection.py
blocktrail/exceptions.py
blocktrail/wallet.py
blocktrail_sdk_beta.egg-info/PKG-INFO
blocktrail_sdk_beta.egg-info/SOURCES.txt
blocktrail_sdk_beta.egg-info/dependency_links.txt
blocktrail_sdk_beta.egg-info/requires.txt
blocktrail_sdk_beta.egg-info/top_level.txt