Metadata-Version: 1.1
Name: blocktrail-sdk-beta
Version: 1.0.6
Summary: BlockTrail's Developer Friendly Bitcoin SDK
Home-page: https://www.blocktrail.com/api/docs/lang/python
Author: Ruben de Vries
Author-email: ruben@blocktrail.com
License: UNKNOWN
Keywords: bitcoin,sdk,api,payments,crypto,wallet,multisig,multisignature,HD wallet
Platform: UNKNOWN
Classifier: Development Status :: 5 - Production/Stable
Classifier: Environment :: Console
Classifier: Environment :: Web Environment
Classifier: Intended Audience :: Developers
Classifier: Programming Language :: Python
Classifier: Programming Language :: Python :: 3
Classifier: License :: OSI Approved :: MIT License
